setup.py
src/mjsrpc2/__init__.py
src/mjsrpc2/rpc.py
src/mjsrpc2.egg-info/PKG-INFO
src/mjsrpc2.egg-info/SOURCES.txt
src/mjsrpc2.egg-info/dependency_links.txt
src/mjsrpc2.egg-info/entry_points.txt
src/mjsrpc2.egg-info/requires.txt
src/mjsrpc2.egg-info/top_level.txt
src/mjsrpc2/ui/__init__.py
src/mjsrpc2/ui/app.py
src/mjsrpc2/ui/cli.py
src/mjsrpc2/ui/clicmd.py