Metadata-Version: 1.1
Name: mjsrpc2
Version: 0.0.7
Summary: mjsrpc2 is a extension of jsonrpc2 providing introspection and argument type validation
Home-page: http://developers.mosaic-cloud.eu
Author: Marian Neagul
Author-email: marian@ieat.ro
License: APL
Keywords: jsonrpc2 rpc
Platform: UNKNOWN
Classifier: Intended Audience :: Developers
Classifier: Development Status :: 3 - Alpha
Classifier: Topic :: Software Development :: Libraries :: Python Modules
Classifier: License :: OSI Approved :: Apache Software License
